pt2keras/__init__.py
pt2keras/main.py
pt2keras/paths.py
pt2keras/onnx_backend/__init__.py
pt2keras/onnx_backend/graph.py
pt2keras/onnx_backend/util.py
pt2keras/onnx_backend/convert/__init__.py
pt2keras/onnx_backend/convert/activations.py
pt2keras/onnx_backend/convert/common.py
pt2keras/onnx_backend/convert/conv.py
pt2keras/onnx_backend/convert/ops.py
pt2keras/onnx_backend/convert/padding.py
pt2keras/onnx_backend/convert/pooling.py
pt2keras/onnx_backend/convert/reshape.py
pt2keras/onnx_backend/testing/__init__.py
pt2keras/onnx_backend/testing/utils.py
pt2keras-0.0.2.2.dist-info/LICENSE
pt2keras-0.0.2.2.dist-info/METADATA
pt2keras-0.0.2.2.dist-info/WHEEL
pt2keras-0.0.2.2.dist-info/top_level.txt
pt2keras-0.0.2.2.dist-info/RECORD
