Metadata-Version: 2.1
Name: pt2keras
Version: 0.0.2.2
Summary: A simple PyTorch to Keras Model converter
Home-page: https://github.com/JWLee89/pt2keras
Author: Jay Lee
Author-email: ljay189@gmail.com
License: UNKNOWN
Platform: UNKNOWN
Classifier: Programming Language :: Python :: 3
Classifier: License :: OSI Approved :: MIT License
Classifier: Operating System :: OS Independent
Requires-Python: >=3.7
License-File: LICENSE
